fastapp/__init__.py
fastapp/main.py
fastapp/auth/__init__.py
fastapp/auth/auth.py
fastapp/auth/password.py
fastapp/auth/users.py
fastapp/core/__init__.py
fastapp/core/logging.py
fastapp/core/mail.py
fastapp/core/settings.py
fastapp/core/models/__init__.py
fastapp/core/models/auth.py
fastapp/core/models/user.py
fastapp/core/templates/reset_password.html
fastapp/db/__init__.py
fastapp/db/db.py
fastapp/db/schema.py
fastapp/routes/__init__.py
fastapp/routes/auth.py
fastapp/tools/fastapp_tools.py
fastapp_framework-1.0.4.dist-info/METADATA
fastapp_framework-1.0.4.dist-info/WHEEL
fastapp_framework-1.0.4.dist-info/entry_points.txt
fastapp_framework-1.0.4.dist-info/top_level.txt
fastapp_framework-1.0.4.dist-info/RECORD
